tabpy_server/startup.bat
tabpy_server/startup.py
tabpy_server/startup.sh
tabpy_server/state.ini.template
tabpy_server/tabpy.py
tabpy_server/common/__init__.py
tabpy_server/common/config.py
tabpy_server/common/endpoint_file_mgr.py
tabpy_server/common/messages.py
tabpy_server/common/tabpy_logging.py
tabpy_server/common/util.py
tabpy_server/management/__init__.py
tabpy_server/management/state.py
tabpy_server/management/util.py
tabpy_server/psws/__init__.py
tabpy_server/psws/callbacks.py
tabpy_server/psws/python_service.py
tabpy_server/static/index.html
tabpy_server/static/tableau.png
tabpy_server-0.2.dist-info/DESCRIPTION.rst
tabpy_server-0.2.dist-info/METADATA
tabpy_server-0.2.dist-info/RECORD
tabpy_server-0.2.dist-info/WHEEL
tabpy_server-0.2.dist-info/metadata.json
tabpy_server-0.2.dist-info/top_level.txt
