Metadata-Version: 2.0
Name: tabpy-server
Version: 0.2
Summary: Web server Tableau uses to run Python scripts.
Home-page: https://github.com/tableau/TabPy
Author: Tableau
Author-email: github@tableau.com
License: MIT
Platform: UNKNOWN
Classifier: Development Status :: 3 - Alpha
Classifier: Intended Audience :: Developers
Classifier: Programming Language :: Python :: 2.7
Classifier: Programming Language :: Python :: 3.5
Classifier: Topic :: Scientific/Engineering
Classifier: Topic :: Scientific/Engineering :: Information Analysis
Requires-Dist: Tornado-JSON
Requires-Dist: cloudpickle
Requires-Dist: decorator
Requires-Dist: future
Requires-Dist: futures
Requires-Dist: genson
Requires-Dist: jsonschema
Requires-Dist: numpy
Requires-Dist: python-dateutil
Requires-Dist: requests
Requires-Dist: simplejson
Requires-Dist: tabpy-client
Requires-Dist: tornado
